{"SimulationMetadata":{"ModelInfo":{"ModelName":"doublepend_2","ModelVersion":"5.15","ModelFilePath":"C:\\Users\\Maurice\\OneDrive\\HTWK\\Regelungstechnik\\double-pendulum\\matlab\\doublepend_2.slx","UserID":"Maurice","MachineName":"DESKTOP-DNGC627","Platform":"PCWIN64","ModelStructuralChecksum":[3167243778,2094152303,3694857069,2287068879],"SimulationMode":"normal","StartTime":0,"StopTime":10,"SolverInfo":{"Type":"Variable-Step","Solver":"ode45","MaxStepSize":0.2},"SimulinkVersion":{"Name":"Simulink","Version":"10.4","Release":"(R2021b)","Date":"14-May-2021"},"LoggingInfo":{"LoggingToFile":"off"}},"TimingInfo":{"WallClockTimestampStart":"2021-11-18 16:05:35","WallClockTimestampStop":"2021-11-18 16:05:36","InitializationElapsedWallTime":1.0562532,"ExecutionElapsedWallTime":0.2043503,"TerminationElapsedWallTime":0.045901000000000004,"TotalElapsedWallTime":1.3065045,"ProfilerData":"Profiler is not enabled"},"ExecutionInfo":{"StopEvent":"ReachedStopTime","StopEventSource":[],"StopEventDescription":"Reached stop time of 10","ErrorDiagnostic":[],"WarningDiagnostics":[{"Diagnostic":{"identifier":"Simulink:Engine:OutputNotConnected","message":"'<a href=\"matlab:slprivate('open_and_hilite_port_hyperlink', 'hilite', ['doublepend_2/Add1'], 'Outport', 1);\">Output Port 1</a>' of '<a href=\"matlab:open_and_hilite_hyperlink ('doublepend_2/Add1','error')\">doublepend_2/Add1</a>' is not connected.","paths":["doublepend_2/Add1"],"cause":[],"stack":[]},"SimulationPhase":"Initialization","SimulationTime":[]},{"Diagnostic":{"identifier":"Simulink:Engine:LineWithoutSrc","message":"Unconnected input line found on '<a href=\"matlab:open_and_hilite_hyperlink ('doublepend_2/nicht-lineares Modell_b1/Demux','error')\">doublepend_2/nicht-lineares Modell_b1/Demux</a>' (input port: 1)","paths":["doublepend_2/nicht-lineares Modell_b1/Demux"],"cause":[],"stack":[]},"SimulationPhase":"Initialization","SimulationTime":[]}]},"UserString":"","UserData":[]},"ErrorMessage":""}